tf_x_transformers/__init__.py
tf_x_transformers/autoregressive_wrapper.py
tf_x_transformers/tf_entmax.py
tf_x_transformers/tf_x_transformers.py
tf_x_transformers-0.0.6.dist-info/METADATA
tf_x_transformers-0.0.6.dist-info/WHEEL
tf_x_transformers-0.0.6.dist-info/top_level.txt
tf_x_transformers-0.0.6.dist-info/RECORD
